LICENCE.md
MANIFEST.in
README.md
setup.cfg
setup.py
fmsne/__init__.py
fmsne/arithmetic_ansi.h
fmsne/arithmetic_sse_double.h
fmsne/arithmetic_sse_float.h
fmsne/fmsne.py
fmsne/fmsne_implem.cpp
fmsne/fmsne_implem.pyx
fmsne/lbfgs.c
fmsne/lbfgs.h
fmsne/vptree.h
fmsne.egg-info/PKG-INFO
fmsne.egg-info/SOURCES.txt
fmsne.egg-info/dependency_links.txt
fmsne.egg-info/requires.txt
fmsne.egg-info/top_level.txt