Metadata-Version: 2.1
Name: fmsne
Version: 0.6.6
Summary: Fast Multi-Scale Neighbour Embedding
Home-page: https://github.com/cdebodt/Fast_Multi-scale_NE
Author: Cyril de Bodt
Author-email: cyril.debodt@uclouvain.be
Maintainer: Laurent Gatto
Maintainer-email: laurent.gatto@uclouvain.be
License: MIT
Platform: any
Classifier: Programming Language :: Python :: 3
Classifier: License :: OSI Approved :: MIT License
Classifier: Operating System :: OS Independent
Classifier: Topic :: Scientific/Engineering :: Bio-Informatics
License-File: LICENCE.md
